auto_reporter/__init__.py
auto_reporter/hook.py
auto_reporter/install.py
auto_reporter/sender.py
auto_reporter-0.2.0.dist-info/METADATA
auto_reporter-0.2.0.dist-info/RECORD
auto_reporter-0.2.0.dist-info/WHEEL
auto_reporter-0.2.0.dist-info/entry_points.txt
auto_reporter-0.2.0.dist-info/top_level.txt
