Metadata-Version: 2.1
Name: auto-reporter
Version: 0.2.0
Summary: Post git commit messages to AT weekly report automatically
Home-page: https://github.com/froyog/auto-reporter
Author: froyog
Author-email: scarlet0345@gmail.com
License: MIT
Platform: UNKNOWN
Classifier: License :: OSI Approved :: MIT License
Classifier: Programming Language :: Python
Classifier: Programming Language :: Python :: 3
Classifier: Programming Language :: Python :: 3.6
Classifier: Programming Language :: Python :: Implementation :: CPython
Classifier: Programming Language :: Python :: Implementation :: PyPy
Requires-Python: >=3.3.0
